<?xml version="1.0" encoding="GBK"?>
<resultMap id="BaseResultMap" type="com.cardpay.pccredit.bank.model.SXykStmtCur">
   <result column="CREATED_TIME" jdbcType="DATE_NOW" index="" style="yyyyMMdd"/>
   <result column="XACCOUNT" index="1" jdbcType="DECIMAL"/>
   <result column="BANK" index="2" jdbcType="DECIMAL"/>
   <result column="CARD_NBR" index="3" jdbcType="VARCHAR"/>
   <result column="CYCLE_NBR" index="4" jdbcType="DECIMAL"/>
   <result column="MONTH_NBR" index="5" jdbcType="DECIMAL"/>
   <result column="POST_DD" index="6" jdbcType="DECIMAL"/>
   <result column="MTHS_ODUE" index="7" jdbcType="DECIMAL"/>
   <result column="PAY_FLAG" index="8" jdbcType="VARCHAR"/>
   <result column="AGE1" index="9" jdbcType="DECIMAL"/>
   <result column="AGE2" index="10" jdbcType="DECIMAL"/>
   <result column="AGE3" index="11" jdbcType="DECIMAL"/>
   <result column="AGE4" index="12" jdbcType="DECIMAL"/>
   <result column="AGE5" index="13" jdbcType="DECIMAL"/>
   <result column="AGE6" index="14" jdbcType="DECIMAL"/>
   <result column="BAL_CMPINT" index="15" jdbcType="DECIMAL"/>
   <result column="BAL_FREE" index="16" jdbcType="DECIMAL"/>
   <result column="BAL_INT" index="17" jdbcType="DECIMAL"/>
   <result column="BALINTFLAG" index="18" jdbcType="VARCHAR"/>
   <result column="BAL_NOINT" index="19" jdbcType="DECIMAL"/>
   <result column="BAL_ORINT" index="20" jdbcType="DECIMAL"/>
   <result column="BRANCH" index="21" jdbcType="DECIMAL"/>
   <result column="BUSINESS" index="22" jdbcType="VARCHAR"/>
   <result column="CARD_FEES" index="23" jdbcType="DECIMAL"/>
   <result column="CASH_ADFEE" index="24" jdbcType="DECIMAL"/>
   <result column="CASH_ADVCE" index="25" jdbcType="DECIMAL"/>
   <result column="CLOSE_BAL" index="26" jdbcType="DECIMAL"/>
   <result column="CLSBAL_FLAG" index="27" jdbcType="VARCHAR"/>
   <result column="CLOSE_CODE" index="28" jdbcType="VARCHAR"/>
   <result column="CLOSE_DATE" index="29" jdbcType="VARCHAR"/>
   <result column="CRED_ADJ" index="30" jdbcType="DECIMAL"/>
   <result column="CRED_LIMIT" index="31" jdbcType="DECIMAL"/>
   <result column="CRED_VOUCH" index="32" jdbcType="DECIMAL"/>
   <result column="CREDLIM_X" index="33" jdbcType="DECIMAL"/>
   <result column="CY_CHGCNT" index="34" jdbcType="DECIMAL"/>
   <result column="CY_CHGDAY" index="35" jdbcType="DECIMAL"/>
   <result column="CY_EFFDAY" index="36" jdbcType="DECIMAL"/>
   <result column="CYCLE_NEW" index="37" jdbcType="DECIMAL"/>
   <result column="DAYSPAY" index="38" jdbcType="DECIMAL"/>
   <result column="DEBIT_ADJ" index="39" jdbcType="DECIMAL"/>
   <result column="DUNCODE1" index="40" jdbcType="VARCHAR"/>
   <result column="DUNCODE2" index="41" jdbcType="VARCHAR"/>
   <result column="DUNCODEB" index="42" jdbcType="VARCHAR"/>
   <result column="DUNLETR1" index="43" jdbcType="VARCHAR"/>
   <result column="DUNLETR2" index="44" jdbcType="VARCHAR"/>
   <result column="DUNLETRB" index="45" jdbcType="VARCHAR"/>
   <result column="DUTY_CREDT" index="46" jdbcType="DECIMAL"/>
   <result column="DUTY_DEBIT" index="47" jdbcType="DECIMAL"/>
   <result column="FEES_TAXES" index="48" jdbcType="DECIMAL"/>
   <result column="INSTL_AMT" index="49" jdbcType="DECIMAL"/>
   <result column="INT_CHDCMP" index="50" jdbcType="DECIMAL"/>
   <result column="INT_CHGD" index="51" jdbcType="DECIMAL"/>
   <result column="INT_CMPOND" index="52" jdbcType="DECIMAL"/>
   <result column="INT_CUNOT" index="53" jdbcType="DECIMAL"/>
   <result column="INT_CURCMP" index="54" jdbcType="DECIMAL"/>
   <result column="INT_EARNED" index="55" jdbcType="DECIMAL"/>
   <result column="INT_RATE" index="56" jdbcType="DECIMAL"/>
   <result column="INT_TAXRTE" index="57" jdbcType="DECIMAL"/>
   <result column="LETR_CODE1" index="58" jdbcType="VARCHAR"/>
   <result column="LETR_CODE2" index="59" jdbcType="VARCHAR"/>
   <result column="LOSSES" index="60" jdbcType="DECIMAL"/>
   <result column="MIN_DUE" index="61" jdbcType="DECIMAL"/>
   <result column="MIN_DUE_DT" index="62" jdbcType="VARCHAR"/>
   <result column="MINDUE_R" index="63" jdbcType="DECIMAL"/>
   <result column="MSG_KEY" index="64" jdbcType="VARCHAR"/>
   <result column="NBR_CASHAD" index="65" jdbcType="DECIMAL"/>
   <result column="NBR_FEEDTY" index="66" jdbcType="DECIMAL"/>
   <result column="NBR_OTHERS" index="67" jdbcType="DECIMAL"/>
   <result column="NBR_PAYMNT" index="68" jdbcType="DECIMAL"/>
   <result column="NBR_PURCH" index="69" jdbcType="DECIMAL"/>
   <result column="ODUE_FLAG" index="70" jdbcType="DECIMAL"/>
   <result column="ODUE_HELD" index="71" jdbcType="DECIMAL"/>
   <result column="OPEN_BAL" index="72" jdbcType="DECIMAL"/>
   <result column="OPBAL_FLAG" index="73" jdbcType="VARCHAR"/>
   <result column="OPEN_DATE" index="74" jdbcType="VARCHAR"/>
   <result column="OTHER_FEES" index="75" jdbcType="DECIMAL"/>
   <result column="PAYMENT" index="76" jdbcType="DECIMAL"/>
   <result column="PAYMT_UNCL" index="77" jdbcType="DECIMAL"/>
   <result column="PEN_CHRG" index="78" jdbcType="DECIMAL"/>
   <result column="POINT_ADJ" index="79" jdbcType="DECIMAL"/>
   <result column="PTADJ_FLAG" index="80" jdbcType="VARCHAR"/>
   <result column="POINT_CLM" index="81" jdbcType="DECIMAL"/>
   <result column="POINT_CUM" index="82" jdbcType="DECIMAL"/>
   <result column="PTFLAG" index="83" jdbcType="VARCHAR"/>
   <result column="POINT_EAR" index="84" jdbcType="DECIMAL"/>
   <result column="PRIOR_NO" index="85" jdbcType="DECIMAL"/>
   <result column="PURCHASES" index="86" jdbcType="DECIMAL"/>
   <result column="QUERY_AMT" index="87" jdbcType="DECIMAL"/>
   <result column="QUERY_CODE" index="88" jdbcType="VARCHAR"/>
   <result column="RECVRY_AMT" index="89" jdbcType="DECIMAL"/>
   <result column="REVCRY_AMT" index="90" jdbcType="DECIMAL"/>
   <result column="STM_AMT_OL" index="91" jdbcType="DECIMAL"/>
   <result column="STMT_CODE" index="92" jdbcType="VARCHAR"/>
   <result column="BAL_MP" index="93" jdbcType="DECIMAL"/>
   <result column="BAL_NINT01" index="94" jdbcType="DECIMAL"/>
   <result column="BAL_NINT02" index="95" jdbcType="DECIMAL"/>
   <result column="BAL_NINT03" index="96" jdbcType="DECIMAL"/>
   <result column="BAL_NINT04" index="97" jdbcType="DECIMAL"/>
   <result column="BAL_NINT05" index="98" jdbcType="DECIMAL"/>
   <result column="BAL_NINT06" index="99" jdbcType="DECIMAL"/>
   <result column="BAL_NINT07" index="100" jdbcType="DECIMAL"/>
   <result column="BAL_NINT08" index="101" jdbcType="DECIMAL"/>
   <result column="BAL_NINT09" index="102" jdbcType="DECIMAL"/>
   <result column="BAL_NINT10" index="103" jdbcType="DECIMAL"/>
   <result column="BAL_CMPFEE" index="104" jdbcType="DECIMAL"/>
   <result column="ORG_NO" index="105" jdbcType="VARCHAR"/>
 </resultMap>